lager_cantools/__init__.py
lager_cantools/compat.py
lager_cantools/errors.py
lager_cantools/j1939.py
lager_cantools/tester.py
lager_cantools/version.py
lager_cantools/database/__init__.py
lager_cantools/database/errors.py
lager_cantools/database/utils.py
lager_cantools/database/can/__init__.py
lager_cantools/database/can/attribute.py
lager_cantools/database/can/attribute_definition.py
lager_cantools/database/can/bus.py
lager_cantools/database/can/c_source.py
lager_cantools/database/can/database.py
lager_cantools/database/can/environment_variable.py
lager_cantools/database/can/internal_database.py
lager_cantools/database/can/message.py
lager_cantools/database/can/node.py
lager_cantools/database/can/signal.py
lager_cantools/database/can/signal_group.py
lager_cantools/database/can/formats/__init__.py
lager_cantools/database/can/formats/arxml.py
lager_cantools/database/can/formats/dbc.py
lager_cantools/database/can/formats/kcd.py
lager_cantools/database/can/formats/sym.py
lager_cantools/database/can/formats/utils.py
lager_cantools/database/diagnostics/__init__.py
lager_cantools/database/diagnostics/data.py
lager_cantools/database/diagnostics/database.py
lager_cantools/database/diagnostics/did.py
lager_cantools/database/diagnostics/internal_database.py
lager_cantools/database/diagnostics/formats/__init__.py
lager_cantools/database/diagnostics/formats/cdd.py
lager_cantools/subparsers/__init__.py
lager_cantools/subparsers/convert.py
lager_cantools/subparsers/decode.py
lager_cantools/subparsers/dump.py
lager_cantools/subparsers/generate_c_source.py
lager_cantools/subparsers/monitor.py
lager_cantools/subparsers/utils.py
lager_cantools-36.1.0.dist-info/LICENSE
lager_cantools-36.1.0.dist-info/METADATA
lager_cantools-36.1.0.dist-info/WHEEL
lager_cantools-36.1.0.dist-info/top_level.txt
lager_cantools-36.1.0.dist-info/RECORD
