Metadata-Version: 2.1
Name: lager-cantools
Version: 36.1.0
Summary: CAN BUS tools.
Home-page: https://github.com/lagerdata/cantools
Author: Erik Moqvist
Author-email: erik.moqvist@gmail.com
License: MIT
Keywords: can,can bus,dbc,kcd,automotive
Platform: UNKNOWN
Classifier: License :: OSI Approved :: MIT License
Classifier: Programming Language :: Python :: 2
Classifier: Programming Language :: Python :: 3
Requires-Dist: bitstruct (>=6.0.0)
Requires-Dist: python-can (>=2.2.0)
Requires-Dist: textparser (>=0.21.1)
Requires-Dist: diskcache
Requires-Dist: argparse-addons
